{
  "resourceType": "Questionnaire",
  "id": "acc-claim-form",
  "status": "active",
  "subjectType": [
    "Patient"
  ],
  "item": [
    {
      "linkId": "pmsSoftware",
      "text": "PMS Software",
      "type": "group",
      "item": [
        {
          "linkId": "pmsSoftwareName",
          "text": "PMS Software Name",
          "type": "string"
        },
        {
          "linkId": "pmsSoftwareVersion",
          "text": "PMS Software Version",
          "type": "string"
        }
      ]
    },
    {
      "linkId": "claimNumber",
      "text": "ACC45 Claim Number",
      "type": "string",
      "required": true
    },
    {
      "linkId": "vendor",
      "text": "Vendor Details",
      "type": "group",
      "item": [
        {
          "linkId": "practiceName",
          "text": "Practice Name",
          "type": "string"
        },
        {
          "linkId": "hpiOrganisationNumber",
          "text": "ACC Vendor ID",
          "type": "string"
        },
        {
          "linkId": "hpiFacilityNumber",
          "text": "ACC Facility Number",
          "type": "string"
        }
      ]
    },
    {
      "linkId": "provider",
      "text": "Provider Details",
      "type": "group",
      "item": [
        {
          "linkId": "providerDetails",
          "text": "Provider Details",
          "type": "group",
          "item": [
            {
              "linkId": "providerId",
              "text": "ACC Provider ID",
              "type": "string"
            },
            {
              "linkId": "providerTypeCode",
              "text": "Provider Type Code",
              "type": "string"
            },
            {
              "linkId": "firstName",
              "text": "First Name",
              "type": "string"
            },
            {
              "linkId": "middleName",
              "text": "Middle Name",
              "type": "string"
            },
            {
              "linkId": "surname",
              "text": "Surname",
              "type": "string"
            }
          ]
        },
        {
          "linkId": "address",
          "text": "Address",
          "type": "group",
          "item": [
            {
              "linkId": "type",
              "text": "Address Type",
              "type": "choice",
              "answerOption": [
                {
                  "valueString": "Home"
                },
                {
                  "valueString": "Postal"
                }
              ]
            },
            {
              "linkId": "line1",
              "text": "Address Line 1",
              "type": "string"
            },
            {
              "linkId": "line2",
              "text": "Address Line 2",
              "type": "string"
            },
            {
              "linkId": "suburb",
              "text": "Suburb",
              "type": "string"
            },
            {
              "linkId": "city",
              "text": "City",
              "type": "string"
            },
            {
              "linkId": "postCode",
              "text": "Post Code",
              "type": "string"
            },
            {
              "linkId": "country",
              "text": "Country",
              "type": "string"
            }
          ]
        }
      ]
    },
    {
      "linkId": "patient",
      "text": "Patient Details",
      "type": "group",
      "item": [
        {
          "linkId": "details",
          "text": "Patient Details",
          "type": "group",
          "item": [
            {
              "linkId": "nhi",
              "text": "National Health Index Number",
              "type": "string"
            },
            {
              "linkId": "firstName",
              "text": "First Name",
              "type": "string"
            },
            {
              "linkId": "middleName",
              "text": "Middle Name",
              "type": "string"
            },
            {
              "linkId": "surname",
              "text": "Surname",
              "type": "string"
            },
            {
              "linkId": "dateOfBirth",
              "text": "Date of Birth",
              "type": "date"
            },
            {
              "linkId": "gender",
              "text": "Gender",
              "type": "choice",
              "answerOption": [
                {
                  "valueString": "M"
                },
                {
                  "valueString": "F"
                },
                {
                  "valueString": "U"
                },
                {
                  "valueString": "O"
                }
              ]
            },
            {
              "linkId": "ethnicityCode",
              "text": "Ethnicity Code",
              "type": "string"
            },
            {
              "linkId": "otherEthnicity",
              "text": "Other Ethnicity",
              "type": "string"
            }
          ]
        },
        {
          "linkId": "occupationCode",
          "text": "Occupation Code",
          "type": "string"
        },
        {
          "linkId": "contact",
          "text": "Contact Information",
          "type": "group",
          "item": [
            {
              "linkId": "emailAddress",
              "text": "Email Address",
              "type": "string"
            },
            {
              "linkId": "mobilePhone",
              "text": "Mobile Phone",
              "type": "string"
            },
            {
              "linkId": "homePhone",
              "text": "Home Phone",
              "type": "string"
            },
            {
              "linkId": "workPhone",
              "text": "Work Phone",
              "type": "string"
            }
          ]
        },
        {
          "linkId": "address",
          "text": "Address",
          "type": "group",
          "item": [
            {
              "linkId": "type",
              "text": "Address Type",
              "type": "choice",
              "answerOption": [
                {
                  "valueString": "Home"
                },
                {
                  "valueString": "Postal"
                }
              ]
            },
            {
              "linkId": "line1",
              "text": "Address Line 1",
              "type": "string"
            },
            {
              "linkId": "line2",
              "text": "Address Line 2",
              "type": "string"
            },
            {
              "linkId": "suburb",
              "text": "Suburb",
              "type": "string"
            },
            {
              "linkId": "city",
              "text": "City",
              "type": "string"
            },
            {
              "linkId": "postCode",
              "text": "Post Code",
              "type": "string"
            },
            {
              "linkId": "country",
              "text": "Country",
              "type": "string"
            }
          ]
        }
      ]
    },
    {
      "linkId": "employment",
      "text": "Employment Details",
      "type": "group",
      "item": [
        {
          "linkId": "inPaidEmployment",
          "text": "In Paid Employment",
          "type": "choice",
          "answerOption": [
            {
              "valueString": "True"
            },
            {
              "valueString": "False"
            }
          ]
        },
        {
          "linkId": "employmentStatusCode",
          "text": "Employment Status Code",
          "type": "string"
        },
        {
          "linkId": "otherEmployment",
          "text": "Other Employment",
          "type": "string"
        },
        {
          "linkId": "workTypeCode",
          "text": "Work Type Code",
          "type": "string"
        },
        {
          "linkId": "employer",
          "text": "Employer Details",
          "type": "group",
          "item": [
            {
              "linkId": "employerName",
              "text": "Employer Name",
              "type": "string"
            },
            {
              "linkId": "address",
              "text": "Employer Address",
              "type": "group",
              "item": [
                {
                  "linkId": "type",
                  "text": "Address Type",
                  "type": "choice",
                  "answerOption": [
                    {
                      "valueString": "Home"
                    },
                    {
                      "valueString": "Postal"
                    }
                  ]
                },
                {
                  "linkId": "line1",
                  "text": "Address Line 1",
                  "type": "string"
                },
                {
                  "linkId": "line2",
                  "text": "Address Line 2",
                  "type": "string"
                },
                {
                  "linkId": "suburb",
                  "text": "Suburb",
                  "type": "string"
                },
                {
                  "linkId": "city",
                  "text": "City",
                  "type": "string"
                },
                {
                  "linkId": "postCode",
                  "text": "Post Code",
                  "type": "string"
                },
                {
                  "linkId": "country",
                  "text": "Country",
                  "type": "string"
                }
              ]
            }
          ]
        }
      ]
    },
    {
      "linkId": "injury",
      "text": "Injury Details",
      "type": "group",
      "item": [
        {
          "linkId": "accidentDate",
          "text": "Accident Date",
          "type": "date"
        },
        {
          "linkId": "accidentLocationCode",
          "text": "Accident Location Code",
          "type": "string"
        },
        {
          "linkId": "accidentSceneCode",
          "text": "Accident Scene Code",
          "type": "string"
        },
        {
          "linkId": "causeOfAccident",
          "text": "Cause of Accident",
          "type": "string"
        },
        {
          "linkId": "involvesVehicle",
          "text": "Involves Vehicle",
          "type": "choice",
          "answerOption": [
            {
              "valueString": "True"
            },
            {
              "valueString": "False"
            }
          ]
        },
        {
          "linkId": "medicalTreatmentInjury",
          "text": "Medical Treatment Injury",
          "type": "choice",
          "answerOption": [
            {
              "valueString": "True"
            },
            {
              "valueString": "False"
            }
          ]
        },
        {
          "linkId": "workInjury",
          "text": "Work Injury",
          "type": "choice",
          "answerOption": [
            {
              "valueString": "True"
            },
            {
              "valueString": "False"
            }
          ]
        },
        {
          "linkId": "sportingInjury",
          "text": "Sporting Injury",
          "type": "choice",
          "answerOption": [
            {
              "valueString": "True"
            },
            {
              "valueString": "False"
            }
          ]
        },
        {
          "linkId": "sportNameCode",
          "text": "Sport Name Code",
          "type": "string"
        },
        {
          "linkId": "gradualProcessInjury",
          "text": "Gradual Process Injury",
          "type": "choice",
          "answerOption": [
            {
              "valueString": "True"
            },
            {
              "valueString": "False"
            }
          ]
        },
        {
          "linkId": "admittedToHospital",
          "text": "Admitted to Hospital",
          "type": "choice",
          "answerOption": [
            {
              "valueString": "True"
            },
            {
              "valueString": "False"
            }
          ]
        },
        {
          "linkId": "injuryComments",
          "text": "Injury Comments",
          "type": "string"
        },
        {
          "linkId": "assistanceRequired",
          "text": "Assistance Required",
          "type": "choice",
          "answerOption": [
            {
              "valueString": "True"
            },
            {
              "valueString": "False"
            }
          ]
        },
        {
          "linkId": "accContactProvider",
          "text": "ACC Contact Provider",
          "type": "string"
        }
      ]
    },
    {
      "linkId": "diagnosis",
      "text": "Diagnosis",
      "type": "group",
      "repeats": true,
      "item": [
        {
          "linkId": "diagnosisCodeType",
          "text": "Diagnosis Code Type",
          "type": "string"
        },
        {
          "linkId": "diagnosisCode",
          "text": "Diagnosis Code",
          "type": "string"
        },
        {
          "linkId": "diagnosisDescription",
          "text": "Diagnosis Description",
          "type": "string"
        },
        {
          "linkId": "diagnosisSide",
          "text": "Diagnosis Side",
          "type": "choice",
          "answerOption": [
            {
              "valueString": "left"
            },
            {
              "valueString": "right"
            },
            {
              "valueString": "notApplicable"
            },
            {
              "valueString": "bilateral"
            }
          ]
        }
      ]
    },
    {
      "linkId": "workCapacity",
      "text": "Work Capacity",
      "type": "group",
      "item": [
        {
          "linkId": "canResumeNormalWork",
          "text": "Can Resume Normal Work",
          "type": "choice",
          "answerOption": [
            {
              "valueString": "True"
            },
            {
              "valueString": "False"
            }
          ]
        },
        {
          "linkId": "incapacity",
          "text": "Incapacity",
          "type": "group",
          "repeats": true,
          "item": [
            {
              "linkId": "incapacityType",
              "text": "Incapacity Type",
              "type": "choice",
              "answerOption": [
                {
                  "valueString": "Fitforselectedwork"
                },
                {
                  "valueString": "Fullyunfitforwork"
                }
              ]
            },
            {
              "linkId": "incapacityDateRange",
              "text": "Incapacity Date Range",
              "type": "group",
              "item": [
                {
                  "linkId": "fromDate",
                  "text": "From Date",
                  "type": "date"
                },
                {
                  "linkId": "toDate",
                  "text": "To Date",
                  "type": "date"
                }
              ]
            },
            {
              "linkId": "selectedAlternativeWork",
              "text": "Selected Alternative Work",
              "type": "group",
              "item": [
                {
                  "linkId": "alternativeWorkTypeCode",
                  "text": "Alternative Work Type Code",
                  "type": "string"
                },
                {
                  "linkId": "physicalRestrictions",
                  "text": "Physical Restrictions",
                  "type": "group",
                  "repeats": true,
                  "item": [
                    {
                      "linkId": "restriction",
                      "text": "Restriction",
                      "type": "choice",
                      "answerOption": [
                        {
                          "valueString": "Lifting"
                        },
                        {
                          "valueString": "Posture"
                        },
                        {
                          "valueString": "Heavy Physical"
                        },
                        {
                          "valueString": "Repetition"
                        },
                        {
                          "valueString": "Vibration"
                        },
                        {
                          "valueString": "Temperature"
                        },
                        {
                          "valueString": "Driving"
                        },
                        {
                          "valueString": "Prolonged Sitting"
                        },
                        {
                          "valueString": "Prolonged Walking"
                        },
                        {
                          "valueString": "Prolonged Standing"
                        },
                        {
                          "valueString": "Other"
                        }
                      ]
                    }
                  ]
                },
                {
                  "linkId": "restrictedHoursPerDay",
                  "text": "Restricted Hours Per Day",
                  "type": "integer"
                },
                {
                  "linkId": "restrictionComment",
                  "text": "Restriction Comment",
                  "type": "string"
                }
              ]
            }
          ]
        },
        {
          "linkId": "returnToNormalWorkDate",
          "text": "Return to Normal Work Date",
          "type": "date"
        }
      ]
    },
    {
      "linkId": "referrals",
      "text": "Referrals",
      "type": "group",
      "repeats": true,
      "item": [
        {
          "linkId": "providerTypeCode",
          "text": "Provider Type Code",
          "type": "string"
        },
        {
          "linkId": "referralReason",
          "text": "Referral Reason",
          "type": "string"
        }
      ]
    },
    {
      "linkId": "declaration",
      "text": "Declaration",
      "type": "group",
      "item": [
        {
          "linkId": "providerDeclaration",
          "text": "Provider Declaration",
          "type": "date"
        }
      ]
    }
  ]
}
