{
  "resourceType": "Questionnaire",
  "meta": {
    "profile": [
      "http://hl7.org/fhir/uv/sdc/StructureDefinition/sdc-questionnaire"
    ]
  },
  "text": {
    "status": "generated",
    "div": "<div xmlns=\"http://www.w3.org/1999/xhtml\"><p class=\"res-header-id\"><b>Generated Narrative: Questionnaire bone-marrow-transplant-waiting-list-registration</b></p><h2>Bone Marrow Transplant Waiting List Registration</h2><p>Initial registration of a patient on the bone marrow transplant waiting list</p><p><i>This questionnaire was generated using the FHIR Questionnaire Designer.</i></p></div>"
  },
  "status": "draft",
  "title": "Bone Marrow Transplant Waiting List Registration",
  "item": [
    {
      "linkId": "p01-waiting-list-registration-details",
      "text": "Waiting List Registration Details",
      "type": "group",
      "prefix": "page 01",
      "required": true,
      "item": [
        {
          "linkId": "p01-g01-q01-referral-date",
          "text": "Referral Date",
          "type": "date",
          "prefix": "page 01 group 01 question 1",
          "required": true
        },
        {
          "linkId": "p01-g01-q02-first-specialist-assessment-fsa-date",
          "text": "First Specialist Assessment (FSA) Date",
          "type": "date",
          "prefix": "page 01 group 01 question 2"
        },
        {
          "linkId": "p01-g01-q03-treatment-location",
          "text": "Treatment Location",
          "type": "choice",
          "prefix": "page 01 group 01 question 3",
          "required": true,
          "answerOption": [
            {
              "valueCoding": {
                "code": "F03067-A",
                "display": "Auckland Hospital"
              }
            },
            {
              "valueCoding": {
                "code": "F06033-K",
                "display": "Wellington Hospital"
              }
            },
            {
              "valueCoding": {
                "code": "F04028-G",
                "display": "Christchurch Hospital"
              }
            },
            {
              "valueCoding": {
                "code": "F04084-F",
                "display": "Palmerston North Hospital"
              }
            },
            {
              "valueCoding": {
                "code": "F05076-A",
                "display": "Waikato Hospital"
              }
            }
          ]
        },
        {
          "linkId": "p01-g01-q04-senior-medical-officer-smo-wellington",
          "text": "Senior Medical Officer (SMO) - Wellington",
          "type": "open-choice",
          "prefix": "page 01 group 01 question 4",
          "answerOption": [
            {
              "valueCoding": {
                "code": "16AMAK",
                "display": "Alwyn D'Souza"
              }
            },
            {
              "valueCoding": {
                "code": "19ASZH",
                "display": "Travis Perera"
              }
            },
            {
              "valueCoding": {
                "code": "17AWZY",
                "display": "Victoria Campion"
              }
            },
            {
              "valueCoding": {
                "code": "28BHRL",
                "display": "Anup George"
              }
            },
            {
              "valueCoding": {
                "code": "12JBNR",
                "display": "Huib Buyck"
              }
            },
            {
              "valueCoding": {
                "code": "15AVPH",
                "display": "Michelle Dickson"
              }
            },
            {
              "valueCoding": {
                "code": "12CKWC",
                "display": "Rob Weinkove"
              }
            },
            {
              "valueCoding": {
                "code": "14HTHQ",
                "display": "Hayden Jina"
              }
            },
            {
              "valueCoding": {
                "code": "29DJPA",
                "display": "Phil George"
              }
            }
          ],
          "enableWhen": [
            {
              "question": "p01-g01-q03-treatment-location",
              "operator": "=",
              "answerCoding": {
                "code": "F06033-K"
              }
            }
          ]
        },
        {
          "linkId": "p01-g01-q07-clinical-nurse-specialist-cns",
          "text": "Wellington Care Team members to add to the careplan",
          "type": "choice",
          "prefix": "page 01 group 01 question 7",
          "repeats": true,
          "answerOption": [
            {
              "valueCoding": {
                "code": "23CATL",
                "display": "Ian McKenzie"
              }
            },
            {
              "valueCoding": {
                "code": "16AMAK",
                "display": "Alwyn D'Souza"
              }
            },
            {
              "valueCoding": {
                "code": "14FMCY",
                "display": "Catherine Wood"
              }
            },
            {
              "valueCoding": {
                "code": "23BXCR",
                "display": "Carol Hua-Yung"
              }
            },
            {
              "valueCoding": {
                "code": "19ASZH",
                "display": "Travis Perera"
              }
            },
            {
              "valueCoding": {
                "code": "17AWZY",
                "display": "Victoria Campion"
              }
            }
          ],
          "enableWhen": [
            {
              "question": "p01-g01-q03-treatment-location",
              "operator": "=",
              "answerCoding": {
                "code": "F06033-K"
              }
            }
          ],
          "extension": [
            {
              "url": "http://hl7.org/fhir/StructureDefinition/questionnaire-itemControl",
              "valueCodeableConcept": {
                "coding": [
                  {
                    "system": "http://hl7.org/fhir/questionnaire-item-control",
                    "code": "check-box",
                    "display": "Check Box"
                  }
                ]
              }
            }
          ]
        },
        {
          "linkId": "p01-g01-q05-senior-medical-officer-smo-auckland",
          "text": "Senior Medical Officer (SMO) - Auckland",
          "type": "open-choice",
          "prefix": "page 01 group 01 question 5",
          "answerOption": [
            {
              "valueCoding": {
                "code": "25CRAX",
                "display": "Clinton Lewis"
              }
            },
            {
              "valueCoding": {
                "code": "18AMAJ",
                "display": "Richard Doocey"
              }
            },
            {
              "valueCoding": {
                "code": "19HSXW",
                "display": "Nicole Chien"
              }
            },
            {
              "valueCoding": {
                "code": "10AGBL",
                "display": "Tim Hawkins"
              }
            },
            {
              "valueCoding": {
                "code": "21AGNT",
                "display": "Sarah Tan"
              }
            }
          ],
          "enableWhen": [
            {
              "question": "p01-g01-q03-treatment-location",
              "operator": "=",
              "answerCoding": {
                "code": "F03067-A"
              }
            }
          ]
        },
        {
          "linkId": "p01-g01-q06-senior-medical-officer-smo-christchurch",
          "text": "Senior Medical Officer (SMO) - Christchurch",
          "type": "open-choice",
          "prefix": "page 01 group 01 question 6",
          "answerOption": [
            {
              "valueCoding": {
                "code": "12ALBG",
                "display": "Andrew Butler"
              }
            },
            {
              "valueCoding": {
                "code": "15AWWY",
                "display": "Blake Hsu"
              }
            },
            {
              "valueCoding": {
                "code": "22DDGC",
                "display": "Amy Holmes"
              }
            },
            {
              "valueCoding": {
                "code": "10HSZY",
                "display": "Catherine Neal"
              }
            },
            {
              "valueCoding": {
                "code": "23ANGP",
                "display": "Sean Macpherson "
              }
            },
            {
              "valueCoding": {
                "code": "19JWFT",
                "display": "Kern Chai"
              }
            },
            {
              "valueCoding": {
                "code": "10ALCT",
                "display": "Peter Ganly"
              }
            },
            {
              "valueCoding": {
                "code": "10ATMG",
                "display": "Emma-Jane McDonald"
              }
            },
            {
              "valueCoding": {
                "code": "24FPPE",
                "display": "Min-Hi Nan"
              }
            }
          ],
          "enableWhen": [
            {
              "question": "p01-g01-q03-treatment-location",
              "operator": "=",
              "answerCoding": {
                "code": "F04028-G"
              }
            }
          ]
        }
      ]
    },
    {
      "linkId": "p02-clinical-details",
      "text": "Clinical Details",
      "type": "group",
      "prefix": "page 02",
      "required": true,
      "item": [
        {
          "linkId": "p02-g01-q01-smo-transplant-clinical-indication-tci-date",
          "text": "SMO Transplant Clinical Indication (TCI) Date",
          "type": "date",
          "prefix": "page 02 group 01 question 1",
          "required": true
        },
        {
          "linkId": "p02-g01-q06-urgency",
          "text": "Urgency Level",
          "type": "choice",
          "prefix": "page 02 group 01 question 6",
          "answerOption": [
            {
              "valueCoding": {
                "system": "http://snomed.info/sct",
                "code": "103391001",
                "display": "Urgent"
              }
            },
            {
              "valueCoding": {
                "system": "http://snomed.info/sct",
                "code": "397943006",
                "display": "Planned"
              }
            },
            {
              "valueCoding": {
                "system": "http://snomed.info/sct",
                "code": "53737009",
                "display": "Acute"
              }
            }
          ]
        },
        {
          "linkId": "p02-g01-q02-disease-indication",
          "text": "Disease Indication",
          "type": "choice",
          "prefix": "page 02 group 01 question 2",
          "required": true,
          "answerOption": [
            {
              "valueCoding": {
                "system": "http://snomed.info/sct",
                "code": "91861009",
                "display": "Acute myeloid leukemia (AML)"
              }
            },
            {
              "valueCoding": {
                "system": "http://snomed.info/sct",
                "code": "91857003",
                "display": "Acute lymphoblastic leukemia (ALL)"
              }
            },
            {
              "valueCoding": {
                "system": "http://snomed.info/sct",
                "code": "109995007",
                "display": "Myelodysplastic syndrome"
              }
            },
            {
              "valueCoding": {
                "system": "http://snomed.info/sct",
                "code": "118601006",
                "display": "Non-Hodgkin lymphoma"
              }
            },
            {
              "valueCoding": {
                "system": "http://snomed.info/sct",
                "code": "109989006",
                "display": "Multiple myeloma"
              }
            },
            {
              "valueCoding": {
                "system": "http://snomed.info/sct",
                "code": "118599009",
                "display": "Hodgkin lymphoma"
              }
            },
            {
              "valueCoding": {
                "system": "http://snomed.info/sct",
                "code": "92814006",
                "display": "Chronic myeloid leukemia (CML)"
              }
            },
            {
              "valueCoding": {
                "system": "http://snomed.info/sct",
                "code": "61180009",
                "display": "Severe aplastic anemia"
              }
            },
            {
              "valueCoding": {
                "system": "http://snomed.info/sct",
                "code": "92814006",
                "display": "Chronic lymphocytic leukemia (CLL)"
              }
            },
            {
              "valueCoding": {
                "system": "http://snomed.info/sct",
                "code": "40108008",
                "display": "Thalassemia major"
              }
            },
            {
              "valueCoding": {
                "system": "http://snomed.info/sct",
                "code": "417357006",
                "display": "Sickle cell disease"
              }
            },
            {
              "valueCoding": {
                "system": "http://snomed.info/sct",
                "code": "31323000",
                "display": "Primary immunodeficiency"
              }
            },
            {
              "valueCoding": {
                "system": "http://snomed.info/sct",
                "code": "307651008",
                "display": "Myelofibrosis"
              }
            },
            {
              "valueCoding": {
                "system": "http://snomed.info/sct",
                "code": "30575002",
                "display": "Fanconi anemia"
              }
            },
            {
              "valueCoding": {
                "system": "http://snomed.info/sct",
                "code": "74733009",
                "display": "Inherited metabolic disorder"
              }
            },
            {
              "valueCoding": {
                "system": "http://snomed.info/sct",
                "code": "79544006",
                "display": "Paroxysmal nocturnal hemoglobinuria"
              }
            },
            {
              "valueCoding": {
                "system": "http://snomed.info/sct",
                "code": "74732009",
                "display": "Amyloidosis"
              }
            },
            {
              "valueCoding": {
                "system": "http://snomed.info/sct",
                "code": "55342001",
                "display": "Neuroblastoma"
              }
            },
            {
              "valueCoding": {
                "system": "http://snomed.info/sct",
                "code": "74964007",
                "display": "Other"
              }
            }
          ]
        },
        {
          "linkId": "p02-g01-q03-patient-type-transplant-type",
          "text": "Patient Type (Transplant Type)",
          "type": "choice",
          "prefix": "page 02 group 01 question 3",
          "required": true,
          "answerOption": [
            {
              "valueCoding": {
                "system": "http://snomed.info/sct",
                "code": "174241000112100",
                "display": "Allogenic HSCT"
              }
            },
            {
              "valueCoding": {
                "code": "709115004",
                "display": "Autologous HSCT"
              }
            },
            {
              "valueCoding": {
                "code": "1156961008",
                "display": "CAR T-cell"
              }
            }
          ]
        },
        {
          "linkId": "p02-g01-q04-treatment-intent",
          "text": "Treatment Intent",
          "type": "open-choice",
          "prefix": "page 02 group 01 question 4",
          "answerOption": [
            {
              "valueCoding": {
                "system": "http://snomed.info/sct",
                "code": "393127004",
                "display": "Curative treatment"
              }
            },
            {
              "valueCoding": {
                "code": "129428001",
                "display": "Non-curative treatment"
              }
            }
          ]
        },
        {
          "linkId": "p02-g01-q05-comments",
          "text": "Comments",
          "type": "text",
          "prefix": "page 02 group 01 question 5"
        }
      ]
    }
  ],
  "description": "Initial registration of a patient on the bone marrow transplant waiting list",
  "version": "0.4.6",
  "publisher": "Te Whatu Ora | Health NZ",
  "date": "2026-07-22T22:52:57.018Z"
}